{
    "fullName": "刘方",
    "contacts": [
        {
            "type": "EMAIL",
            "contact": "leo.liu@originplus.com"
        },
        {
            "type": "LINKEDIN",
            "contact": "liu-fang-%E5%88%98%E6%96%B9-4556406"
        }
    ],
    "educations": [
        {
            "startDate": "2004-01-01",
            "endDate": "2007-01-01",
            "collegeName": "JiangnanUniversity",
            "degreeLevel": "MASTER",
            "majorName": "(Industrial and Product )?Design"
        },
        {
            "startDate": "1993-01-01",
            "endDate": "1993-12-31",
            "collegeName": "JiangnanUniversity",
            "degreeLevel": "BACHELOR",
            "majorName": "(Industrial and Product)? Design"
        }
    ],
    "experiences": [
        {
            "description": "本然创新成立于2009年\\W*是中国产品创新咨询服务的先行者\\W*我们致力于帮助\\W*企业发现和定义新产品的机会\\W*概念与策略\\W*我们的客户是来自不同而领域的\\W*领导企业\\W*耳熟能详的名字包括科勒\\W*索尼\\W*三星\\W*OPPO\\W*魅族\\W*联想\\W*广汽\\W*丰田\\W*广汽传祺\\W*长安汽车\\W*博士西门子\\W*惠而浦\\W*苏泊尔\\W*方太\\W*老板\\W*美\\W*的\\W*长虹\\W*奥克斯\\W*阿克苏诺贝尔\\W*罗莱家纺\\W*迪卡侬\\W*奥的斯\\W*3M\\W*通力等\\W*Established\\W*in\\W*2009\\W*ORIGIN\\W*is\\W*the\\W*pioneer\\W*of\\W*product\\W*innovation\\W*consulting\\W*firm\\W*in\\W*China\\W*We\\W*are\\W*dedicated\\W*in\\W*helping\\W*business\\W*discover\\W*and\\W*define\\W*the\\W*opportunity\\W*concept\\W*and\\W*strategy\\W*for\\W*new\\W*product\\W*Our\\W*clients\\W*consist\\W*of\\W*leaders\\W*from\\W*various\\W*industries\\W*including\\W*those\\W*well\\W*known\\W*names\\W*Kohler\\W*Sony\\W*Samsung\\W*OPPO\\W*Meizu\\W*Lenovo\\W*TOYOTA\\W*GuangZhou\\W*Auto\\W*ChangAn\\W*Auto\\W*BSH\\W*Whirlpool\\W*Supor\\W*Fotile\\W*Robam\\W*Midea\\W*Changhong\\W*Aux\\W*AkzonNobel\\W*LuoLai\\W*Decathlon\\W*Otis\\W*3M\\W*KONE\\W*etc\\W*",
            "companyName": "ORIGIN\\W{0,2}",
            "title": "Founder & CEO",
            "startDate": "2009-07-01",
            "current": true
        },
        {
            "description": "Page\\W*1\\W*of\\W*3\\W*https\\W*www\\W*linkedin\\W*com\\W*in\\W*liu\\W*fang\\W*E5\\W*88\\W*98\\W*E6\\W*96\\W*B9\\W*4556406\\W*jobid\\W*1234\\W*lipi\\W*urn\\W*3Ali\\W*3Apage\\W*3Ad_jobs_easyapply_pdfgenresume\\W*3Ben3GGYUQRjiybvlHX3niPA\\W*3D\\W*3D\\W*licu\\W*urn\\W*3Ali\\W*3Acontrol\\W*3Ad_jobs_easyapply_pdfgenresume\\W*v02_profile\\W*https\\W*www\\W*linkedin\\W*com\\W*in\\W*liu\\W*fang\\W*E5\\W*88\\W*98\\W*E6\\W*96\\W*B9\\W*4556406\\W*jobid\\W*1234\\W*lipi\\W*urn\\W*3Ali\\W*3Apage\\W*3Ad_jobs_easyapply_pdfgenresume\\W*3Ben3GGYUQRjiybvlHX3niPA\\W*3D\\W*3D\\W*licu\\W*urn\\W*3Ali\\W*3Acontrol\\W*3Ad_jobs_easyapply_pdfgenresume\\W*v02_profile\\W*https\\W*www\\W*linkedin\\W*com\\W*in\\W*liu\\W*fang\\W*E5\\W*88\\W*98\\W*E6\\W*96\\W*B9\\W*4556406\\W*jobid\\W*1234\\W*lipi\\W*urn\\W*3Ali\\W*3Apage\\W*3Ad_jobs_easyapply_pdfgenresume\\W*3Ben3GGYUQRjiybvlHX3niPA\\W*3D\\W*3D\\W*licu\\W*urn\\W*3Ali\\W*3Acontrol\\W*3Ad_jobs_easyapply_pdfgenresume\\W*v02_profile\\W*http\\W*www\\W*originplus\\W*com\\W*head\\W*of\\W*new\\W*product\\W*development\\W*to\\W*develop\\W*a\\W*biomass\\W*energy\\W*solution\\W*to\\W*help\\W*consumer\\W*in\\W*rural\\W*area\\W*in\\W*emerging\\W*country\\W*have\\W*a\\W*cleaner\\W*safer\\W*and\\W*more\\W*affordable\\W*living\\W*in\\W*kitchen\\W*",
            "companyName": "BP",
            "title": "Director Of Product Development",
            "startDate": "2008-05-01",
            "endDate": "2009-05-01"
        },
        {
            "description": "6\\W*years\\W*Establishing\\W*China\\W*studio\\W*of\\W*global\\W*design\\W*from\\W*scratch\\W*covering\\W*the\\W*region\\W*of\\W*greater\\W*China\\W*Indian\\W*East\\W*Europe\\W*and\\W*Latin\\W*American\\W*serving\\W*all\\W*modalities\\W*in\\W*a\\W*full\\W*spectrum\\W*product\\W*definition\\W*product\\W*design\\W*UX\\W*UI\\W*design\\W*and\\W*service\\W*design\\W*Paying\\W*great\\W*efforts\\W*to\\W*place\\W*design\\W*in\\W*a\\W*more\\W*strategic\\W*role\\W*in\\W*the\\W*ICFC\\W*in\\W*China\\W*for\\W*China\\W*strategy\\W*for\\W*GE\\W*Healthcare\\W*making\\W*design\\W*the\\W*partner\\W*of\\W*product\\W*strategy\\W*and\\W*planning\\W*in\\W*the\\W*very\\W*early\\W*stage\\W*of\\W*NPD\\W*process\\W*Introducing\\W*User\\W*centric\\W*approach\\W*and\\W*design\\W*thinking\\W*to\\W*whole\\W*R\\W*D\\W*and\\W*product\\W*organization\\W*",
            "companyName": "GEHealthcare",
            "title": "Design Director",
            "startDate": "2006-05-01",
            "endDate": "2008-06-01"
        },
        {
            "description": "product\\W*organization\\W*Leading\\W*the\\W*design\\W*team\\W*for\\W*global\\W*marketing\\W*GE\\W*Plastics\\W*reporting\\W*to\\W*GM\\W*of\\W*global\\W*design\\W*Using\\W*design\\W*as\\W*a\\W*tool\\W*to\\W*explore\\W*the\\W*future\\W*opportunity\\W*of\\W*the\\W*innovative\\W*application\\W*of\\W*plastic\\W*resin\\W*which\\W*gave\\W*critical\\W*possibilities\\W*for\\W*marketing\\W*strategy\\W*and\\W*material\\W*R\\W*D\\W*as\\W*well\\W*Closely\\W*collaborating\\W*with\\W*industry\\W*leaders\\W*on\\W*the\\W*most\\W*forward\\W*looking\\W*areas\\W*such\\W*as\\W*renewable\\W*energy\\W*house\\W*high\\W*speed\\W*train\\W*electric\\W*vehicle\\W*mobile\\W*computing\\W*etc\\W*",
            "companyName": "GEHealthcare",
            "title": "Design Manager",
            "startDate": "2004-07-01",
            "endDate": "2006-05-01"
        },
        {
            "description": "computing\\W*etc\\W*Working\\W*as\\W*a\\W*senior\\W*design\\W*consultant\\W*for\\W*GE\\W*FITCH\\W*which\\W*was\\W*a\\W*joint\\W*venture\\W*of\\W*GE\\W*Plastic\\W*and\\W*Fitch\\W*worldwide\\W*at\\W*the\\W*time\\W*Providing\\W*pretty\\W*hard\\W*core\\W*design\\W*services\\W*such\\W*as\\W*DFMA\\W*to\\W*GE\\W*Plastics\\W*and\\W*strategic\\W*design\\W*services\\W*such\\W*as\\W*PI\\W*product\\W*identity\\W*to\\W*other\\W*clients\\W*in\\W*Greater\\W*China\\W*and\\W*SEA\\W*",
            "companyName": "GEHealthcare",
            "title": "Senior Design Consultant",
            "startDate": "2002-07-01",
            "endDate": "2004-07-01"
        },
        {
            "description": "Page\\W*2\\W*of\\W*3\\W*As\\W*the\\W*pioneer\\W*of\\W*in\\W*house\\W*industrial\\W*designer\\W*in\\W*China\\W*providing\\W*product\\W*design\\W*service\\W*to\\W*Midea\\W*and\\W*other\\W*benefit\\W*conflict\\W*free\\W*external\\W*clients\\W*Beside\\W*using\\W*the\\W*very\\W*old\\W*school\\W*design\\W*techniques\\W*of\\W*hand\\W*sketching\\W*hand\\W*rendering\\W*and\\W*hand\\W*made\\W*prototypes\\W*we\\W*were\\W*the\\W*pioneers\\W*of\\W*adopting\\W*contemporary\\W*design\\W*techniques\\W*such\\W*2D\\W*rendering\\W*3D\\W*modeling\\W*and\\W*3D\\W*printing\\W*back\\W*then\\W*As\\W*the\\W*major\\W*driver\\W*to\\W*help\\W*import\\W*user\\W*centric\\W*approach\\W*into\\W*design\\W*process\\W*including\\W*adoption\\W*of\\W*user\\W*research\\W*and\\W*UX\\W*UI\\W*design\\W*",
            "companyName": "Midea",
            "title": "lead designer / design manager",
            "startDate": "1997-08-01",
            "endDate": "2002-03-01"
        }
    ],
    "skills": [
        {
            "skillName": "UI"
        }
    ]
}