{
    "all": 24,
    "important": 23,
    "desc": 1,
    "correct_important": 9,
    "correct_desc": 0,
    "additional": 0,
    "important_keys": {
        "contacts.2": false,
        "educations.0.degreeLevel": false,
        "educations.0.majorName": false,
        "educations.1.degreeLevel": false,
        "educations.1.majorName": false,
        "experiences.0.companyName": false,
        "experiences.0.title": false,
        "experiences.0.startDate": false,
        "experiences.0.endDate": false,
        "skills.0.skillName": false,
        "skills.1.skillName": false,
        "skills.2.skillName": false,
        "skills.3.skillName": false,
        "skills.4.skillName": false
    },
    "unimportant_keys": {
        "experiences.0.description": false
    },
    "addition_info_count": 0,
    "addition_info": {}
}